{"id": 26474, "term": "Spring 2023 Wenzhou", "termcode": "23/SPWZ", "SubjectCode": "CPS", "Number": "2231", "title": "COMPUTER PROGRAMMING", "section": "W01", "prof": [], "days": [[1, 3], [1, 3]], "starttime": ["08:30:00", "09:15:00"], "endtime": ["09:15:00", "10:15:00"], "startdate": ["/Date(1676264400000)/", "/Date(1676264400000)/"], "enddate": ["/Date(1685419200000)/", "/Date(1685419200000)/"], "capacity": 22, "Requisites": [], "credits": "4.0", "description": "Fundamental computing and programming concerts; use of systems software; problem solving; design of algorithms using a high-level, object-oriented programming language.", "comments": "WENZHOU-KEAN STUDENTS ONLY.  CNAHS STUDENTS ONLY."}